x509creds/__init__.py
x509creds/_models.py
x509creds/utils.py
x509creds/_vendor/__init__.py
x509creds/_vendor/crypto.py
x509creds/_vendor/pyopenssl.py
x509creds/encoding/__init__.py
x509creds/encoding/_decoders.py
x509creds/encoding/_utils.py
x509creds/encoding/der.py
x509creds/encoding/pem.py
x509creds/encoding/pkcs12.py
x509creds-0.10.2.dist-info/METADATA
x509creds-0.10.2.dist-info/WHEEL
x509creds-0.10.2.dist-info/top_level.txt
x509creds-0.10.2.dist-info/RECORD
