Metadata-Version: 2.1
Name: x509creds
Version: 0.10.2
Summary: SSLContext and SSLSocket interfaces
Home-page: https://github.com/jose-pr/pypki
Author: Jose A.
Author-email: jose-pr@coqui.dev
License: UNKNOWN
Platform: UNKNOWN
Requires-Dist: cryptography (>=36)
Requires-Dist: pyopenssl ; extra == "pyopenssl"
